dc/README.md
dc/app.py
dc/mtxdc.egg-info/PKG-INFO
dc/mtxdc.egg-info/SOURCES.txt
dc/mtxdc.egg-info/dependency_links.txt
dc/mtxdc.egg-info/entry_points.txt
dc/mtxdc.egg-info/not-zip-safe
dc/mtxdc.egg-info/requires.txt
dc/mtxdc.egg-info/top_level.txt
mtxdc-0.0.78.dist-info/METADATA
mtxdc-0.0.78.dist-info/WHEEL
mtxdc-0.0.78.dist-info/entry_points.txt
mtxdc-0.0.78.dist-info/top_level.txt
mtxdc-0.0.78.dist-info/RECORD
