Metadata-Version: 2.1
Name: mtxdc
Version: 0.0.78
Summary: The funniest joke in the world
Home-page: http://github.com/storborg/funniest
Author: Flying Circus
Author-email: flyingcircus@example.com
License: MIT
Keywords: funniest joke comedy flying circus
Platform: UNKNOWN
Classifier: Development Status :: 3 - Alpha
Classifier: License :: OSI Approved :: MIT License
Classifier: Programming Language :: Python :: 2.7
Classifier: Topic :: Text Processing :: Linguistic
Requires-Dist: flask
Requires-Dist: pyyaml
Requires-Dist: python-dotenv
Requires-Dist: requests (>=2.26.0)
Requires-Dist: celery
